NOTICE.html
pyaimopt/__init__.py
pyaimopt/aim_credentials.py
pyaimopt/azure_test.py
pyaimopt/azure_workspace.py
pyaimopt/builder.py
pyaimopt/constants.py
pyaimopt/description.py
pyaimopt/LICENSE
pyaimopt/platform.py
pyaimopt/problem.py
pyaimopt/serialization.py
pyaimopt/solver.py
pyaimopt/use.txt
pyaimopt/workspace.py
pyaimopt-0.7.5.dist-info/entry_points.txt
pyaimopt-0.7.5.dist-info/LICENSE
pyaimopt-0.7.5.dist-info/METADATA
pyaimopt-0.7.5.dist-info/WHEEL
pyaimopt-0.7.5.dist-info/RECORD
