Metadata-Version: 2.1
Name: pyaimopt
Version: 0.7.5
Summary: 
License: Proprietary
Author: Project AIM
Author-email: project-aim-contact@microsoft.com
Requires-Python: >=3.8,<4.0
Classifier: License :: Other/Proprietary License
Classifier: Programming Language :: Python :: 3
Classifier: Programming Language :: Python :: 3.8
Classifier: Programming Language :: Python :: 3.9
Classifier: Programming Language :: Python :: 3.10
Classifier: Programming Language :: Python :: 3.11
Requires-Dist: anyio (>=3.6.2,<4.0.0)
Requires-Dist: azure-core (>=1.26.3,<2.0.0)
Requires-Dist: azure-identity (>=1.12.0,<2.0.0)
Requires-Dist: azure-storage-blob (>=12.15.0,<13.0.0)
Requires-Dist: json5 (>=0.9.11,<0.10.0)
Requires-Dist: networkx (>=3.0,<4.0)
Requires-Dist: numpy (>=1.24.2,<2.0.0)
Requires-Dist: packaging (>=23.2,<24.0)
Requires-Dist: platformdirs (>=3.5.1,<4.0.0)
Requires-Dist: python-dotenv (>=1.0.0,<2.0.0)
Requires-Dist: scipy (>=1.10.1,<2.0.0) ; python_version >= "3.8" and python_version < "3.12"
